plib/dbtools/__init__.py
plib/dbtools/mysql.py
plib/dbtools/sqlite.py
plib/test/dbtools/__init__.py
plib/test/dbtools/__main__.py
plib/test/dbtools/test_dbtools.py
plib3.dbtools-1.3.1.dist-info/LICENSE.txt
plib3.dbtools-1.3.1.dist-info/METADATA
plib3.dbtools-1.3.1.dist-info/WHEEL
plib3.dbtools-1.3.1.dist-info/top_level.txt
plib3.dbtools-1.3.1.dist-info/RECORD
